[{"type":"audio","fullpath":"\/home\/cshome\/h\/hpark\/Desktop\/testing.mp3","metadata":{"audio_Name":"Batman_Snoring","genre":"Recording","creator":"Cat_Woman","runtime":"00:12:32","date":"24\/05\/2012"}},{"type":"audio","fullpath":"\/home\/cshome\/h\/hpark\/Desktop\/motivation.mp3","metadata":{"audio_Name":"Discovery_Channel","genre":"Rock","creator":"Blood_Hound_Gang","runtime":"00:03:31","date":"19\/03\/2008"}},{"type":"audio","fullpath":"\/home\/desktop\/jokes\/Ilovecosc346.mp3","metadata":{"audio_Name":"Phone_Call_Between_Paul_and_Hamza","genre":"Recording","creator":"NSA","runtime":"00:39:12","date":"14\/02\/2018"}},{"type":"audio","fullpath":"\/home\/desktop\/ohdamn\/sotired.mp3","metadata":{"audio_Name":"Fly_Kicks","genre":"Electro_House","creator":"AC_Slater","runtime":"00:4:38","date":"21\/08\/2016"}},{"type":"document","fullpath":"\/home\/cshome\/h\/hpark\/Desktop\/IHATEMYSELF.txt","metadata":{"file_Location":"~\/NotTiare\/NotDesktop","file_Size":"12MB","last_Modified":"12\/7\/2018","creator":"Not_Grace","file_Name":"Assignment_are_Fun"}},{"type":"document","fullpath":"\/home\/cshome\/h\/hpark\/Desktop\/life.txt","metadata":{"file_Location":"~\/NotTiare\/NotDesktop\/MaybePregnant","file_Size":"500MB","last_Modified":"07\/07\/2017","creator":"Not_Tiare","file_Name":"Baby_Shower_Invitations"}},{"type":"document","fullpath":"\/home\/desktop\/an\/ass.txt","metadata":{"file_Location":"~\/NotTiare\/NotDesktop\/Trash","file_Size":"12KB","last_Modified":"01\/2\/2012","creator":"Shasha","file_Name":"Reasons_To_Live"}},{"type":"document","fullpath":"\/home\/desktop\/whut\/isgoingon.txt","metadata":{"file_Location":"~\/NotTiare\/NotDesktop\/University","file_Size":"50MB","last_Modified":"03\/07\/2013","creator":"Maybe_Hamza","file_Name":"Letter_of_Acceptence"}},{"type":"image","fullpath":"\/home\/cshome\/h\/hpark\/Desktop\/test.jpg","metadata":{"time_Of_Date":"25\/12\/2018_13:31:07","image Name":"Booty_Pics","creator":"Nicky_Minaj","location":"Dunedin_City","resolution":"640x480"}},{"type":"image","fullpath":"\/home\/cshome\/h\/hpark\/Desktop\/test2.jpg","metadata":{"time_Of_Date":"12\/09\/2007_16:21:02","image_Name":"Photo_of_Parents","creator":"Batman","location":"Gotham_City","resolution":"1440x1080"}},{"type":"image","fullpath":"\/home\/desktop\/Shh\/PirateBay.jpg","metadata":{"time_Of_Date":"01\/02\/1521_12:38:52","image_Name":"Jar_of_Dirt","creator":"Jack_Sparrow","location":"Mexico_City","resolution":"960x720"}},{"type":"image","fullpath":"\/home\/desktop\/NSA\/BadGuy.jpg","metadata":{"time_Of_Date":"25\/12\/2018_13:31:07","image_Name":"Snowden_Sighting","creator":"FBI_Guy","location":"Russia","resolution":"2560x1600"}},{"type":"video","fullpath":"\/home\/cshome\/h\/hpark\/Desktop\/video-1538203914.mp4","metadata":{"resolution":"4k","video_Size":"50MB","creator":"Mum","runtime":"00:15:25","video_Name":"Funny_Cat_Videos"}},{"type":"video","fullpath":"\/home\/cshome\/h\/hpark\/Desktop\/grace.mp4","metadata":{"resolution":"1080p","video_Size":"2GB","creator":"Little_Brother","runtime":"01:30:15","video_Name":"Crazy_Frog"}},{"type":"video","fullpath":"\/home\/desktop\/please\/benice.mp4","metadata":{"resolution":"240p","video_Size":"5MB","creator":"Logan","runtime":"00:12:01","video_Name":"Filmed_By_a_Potato"}},{"type":"video","fullpath":"\/home\/desktop\/aplus\/aplause.mp4","metadata":{"resolution":"720p","video_Size":"500MB","creator":"Batman","runtime":"00:22:55","video_Name":"Monster_Hunter_Worlds:_GunLance_Tutorial"}}]